{
  "hash": "8a48bc8b22dc9381b3b00e4422d7b279",
  "result": {
    "markdown": "---\ntitle: \"Welcome\"\neditor: visual\n---\n\n\n## How to use this site\n\nThis site contains R code and some explanatory text to help with completing the data analyses for ANIM5502 in 2022.\n\nCode from each section can be copied using the clipboard symbol on the right of each 'code block' (the grey boxes). You can try this below.\n\n\n::: {.cell}\n\n```{.r .cell-code}\nprint(\"Success - too easy to copy and paste code\")\n```\n:::\n\n\nAlso, did you happen to hover over 'print' in the above code? If not try it - clicking on a function name will take you to its online help page.",
    "supporting": [],
    "filters": [
      "rmarkdown/pagebreak.lua"
    ],
    "includes": {
      "include-in-header": [
        "<link href=\"site_libs/pagedtable-1.1/css/pagedtable.css\" rel=\"stylesheet\" />\r\n<script src=\"site_libs/pagedtable-1.1/js/pagedtable.js\"></script>\r\n"
      ]
    },
    "engineDependencies": {},
    "preserve": {},
    "postProcess": true
  }
}